xsd2rdf/XSDtoRDF.py
xsd2rdf/__init__.py
xsd2rdf/__main__.py
xsd2rdf/utils.py
xsd2rdf-1.1.1.dist-info/METADATA
xsd2rdf-1.1.1.dist-info/WHEEL
xsd2rdf-1.1.1.dist-info/entry_points.txt
xsd2rdf-1.1.1.dist-info/licenses/LICENSE
xsd2rdf-1.1.1.dist-info/RECORD
