Metadata-Version: 2.4
Name: xsd2rdf
Version: 1.1.1
Summary: Generates OWL, SHACL shapes and SKOS concepts from XML Schema (XSD) files
License: EUPL-1.2
License-File: LICENSE
Author: Mathias Vanden Auweele
Author-email: mathias@matdata.eu
Requires-Python: >=3.9,<4.0
Classifier: Development Status :: 3 - Alpha
Classifier: Environment :: Console
Classifier: Intended Audience :: Science/Research
Classifier: License :: OSI Approved :: European Union Public Licence 1.2 (EUPL 1.2)
Classifier: Operating System :: OS Independent
Classifier: Programming Language :: Python
Classifier: Programming Language :: Python :: 3
Classifier: Programming Language :: Python :: 3.9
Classifier: Programming Language :: Python :: 3.10
Classifier: Programming Language :: Python :: 3.11
Classifier: Programming Language :: Python :: 3.12
Classifier: Programming Language :: Python :: 3.13
Classifier: Programming Language :: Python :: 3.14
Classifier: Programming Language :: Python :: 3 :: Only
Classifier: Topic :: File Formats
Classifier: Topic :: Scientific/Engineering
Classifier: Topic :: Software Development :: Libraries :: Python Modules
Requires-Dist: pyshacl (>0.30.0)
Requires-Dist: rdflib (>7.1.0)
Project-URL: Repository, https://gitlab.com/era-europa-eu/public/interoperable-data-programme/era-ontology/xsd2rdf
